tensile_test/__init__.py
tensile_test/_version.py
tensile_test/hardening.py
tensile_test/leven_marq.py
tensile_test/tensile_test.py
tensile_test/utils.py
tensile_test-0.1.3.dist-info/LICENSE
tensile_test-0.1.3.dist-info/METADATA
tensile_test-0.1.3.dist-info/WHEEL
tensile_test-0.1.3.dist-info/top_level.txt
tensile_test-0.1.3.dist-info/RECORD
