Metadata-Version: 2.1
Name: tensile-test
Version: 0.1.3
Summary: A package for analysing the results of tensile tests.
Home-page: UNKNOWN
Author: Adam J. Plowman
Author-email: adam.plowman@manchester.ac.uk
License: UNKNOWN
Project-URL: Github, https://github.com/LightForm-group/tensile-test
Platform: UNKNOWN
Classifier: Development Status :: 4 - Beta
Classifier: Intended Audience :: Science/Research
Classifier: Topic :: Scientific/Engineering
Classifier: Programming Language :: Python :: 3.5
Classifier: Programming Language :: Python :: 3.6
Classifier: Programming Language :: Python :: 3.7
Classifier: License :: OSI Approved :: Mozilla Public License 2.0 (MPL 2.0)
Classifier: Operating System :: OS Independent
Requires-Dist: numpy
Requires-Dist: plotly
Requires-Dist: ipywidgets
